interpret/__init__.py
interpret/core.py
interpret/hooks.py
interpret/imagenet.py
interpret/misc.py
interpret/override.py
interpret/plots.py
interpret/transforms.py
interpret/utils.py
interpret/attr/__init__.py
interpret/attr/attribute.py
interpret/attr/gradcam.py
interpret/attr/gradient.py
interpret/attr/guidedback.py
interpret/attr/integrated_grads.py
interpret/models/__init__.py
interpret/models/cppn.py
interpret/models/layers.py
interpret/vis/__init__.py
interpret/vis/objective.py
interpret/vis/optvis.py
interpret/vis/param.py
test/__init__.py
test/conftest.py
test/test_cppn.py
test/test_gradcam.py
test/test_guided.py
test/test_misc.py
test/test_transforms.py
test/test_utils.py
test/test_vis.py
test/test_vis_objectives.py
test/test_vis_params.py
interpret_pytorch-0.2.1.dist-info/LICENSE
interpret_pytorch-0.2.1.dist-info/METADATA
interpret_pytorch-0.2.1.dist-info/WHEEL
interpret_pytorch-0.2.1.dist-info/top_level.txt
interpret_pytorch-0.2.1.dist-info/RECORD
