Metadata-Version: 2.1
Name: interpret-pytorch
Version: 0.2.1
Summary: Interpreting deep learning models in PyTorch.
Home-page: https://github.com/ttumiel/interpret
Author: Thomas Tumiel
License: UNKNOWN
Platform: UNKNOWN
Classifier: Programming Language :: Python :: 3
Classifier: Operating System :: OS Independent
Classifier: Development Status :: 3 - Alpha
Classifier: License :: OSI Approved :: MIT License
Requires-Python: >=3.6
Requires-Dist: numpy
Requires-Dist: matplotlib
Requires-Dist: pandas
Requires-Dist: Pillow
Requires-Dist: tqdm
Requires-Dist: torchvision
Requires-Dist: torch
Provides-Extra: test
Requires-Dist: coverage ; extra == 'test'
Requires-Dist: pytest ; extra == 'test'
Requires-Dist: scikit-learn ; extra == 'test'
